{
    "board": [
        [0, 0, 0, 0, 0],
        [0, 0, 0, 0, 0],
        [0, 0, 0, 0, 0],
        [0, 0, 0, 0, 0],
        [0, 0, 0, 0, 0]
    ],
    "boardHash": "19261153649140605024552417994922546473530072875902678653210025980873274131905",
    "resourceState": [
        [
            [0, 0, 0, 0, 0],
            [0, 0, 0, 0, 0],
            [0, 0, 0, 0, 0],
            [0, 0, 0, 0, 0],
            [0, 0, 0, 0, 0]
        ],
        [
            [0, 0, 0, 0, 0],
            [0, 0, 0, 0, 0],
            [0, 0, 0, 0, 0],
            [0, 0, 0, 0, 0],
            [0, 0, 0, 0, 0]
        ]
    ],
    "stateHash": "19566192433199768019714648174629306541205224169280620721690837488103428951668",
    "resourceInput": [0, 0]
}